Workbook

Sheet Executive_Summary
A1: E-COMMERCE SALES & CUSTOMER PERFORMANCE MODEL
A2: Dataset: 50 Transactions | Validated: 48 Orders | Currency: INR (₹)
B4: TOTAL REVENUE (₹) | D4: TOTAL ORDERS | F4: AVERAGE ORDER VALUE (₹) | H4: TOTAL UNITS SOLD
B5: =SUM(Cleaned_Sales!K2:K50) | D5: =COUNTA(Cleaned_Sales!A2:A50) | F5: =AVERAGE(Cleaned_Sales!K2:K50) | H5: =SUM(Cleaned_Sales!G2:G50)
A8: Category Breakdown (Formulas: COUNTIFS, SUMIFS, IF)
A9: Category | B9: Orders (COUNTIFS) | C9: Revenue (SUMIFS) | D9: Revenue Share % | E9: Performance Status
A10: Clothing | B10: =COUNTIFS(Cleaned_Sales!E:E, A10) | C10: =SUMIFS(Cleaned_Sales!K:K, Cleaned_Sales!E:E, A10) | D10: =C10/$B$5 | E10: =IF(C10>500000, "High Revenue", "Moderate")
A11: Electronics | B11: =COUNTIFS(Cleaned_Sales!E:E, A11) | C11: =SUMIFS(Cleaned_Sales!K:K, Cleaned_Sales!E:E, A11) | D11: =C11/$B$5 | E11: =IF(C11>500000, "High Revenue", "Moderate")
A12: Furniture | B12: =COUNTIFS(Cleaned_Sales!E:E, A12) | C12: =SUMIFS(Cleaned_Sales!K:K, Cleaned_Sales!E:E, A12) | D12: =C12/$B$5 | E12: =IF(C12>500000, "High Revenue", "Moderate")
A16: Regional Sales Breakdown (SUMIFS, COUNTIFS, IFERROR)
A17: Region | B17: Orders | C17: Revenue (₹) | D17: Regional AOV (₹) | E17: Target Status
A18: East | B18: =COUNTIFS(Cleaned_Sales!D:D, A18) | C18: =SUMIFS(Cleaned_Sales!K:K, Cleaned_Sales!D:D, A18) | D18: =IFERROR(C18/B18, 0) | E18: =IF(C18>250000, "Top Market", "Developing")
A19: North | B19: =COUNTIFS(Cleaned_Sales!D:D, A19) | C19: =SUMIFS(Cleaned_Sales!K:K, Cleaned_Sales!D:D, A19) | D19: =IFERROR(C19/B19, 0) | E19: =IF(C19>250000, "Top Market", "Developing")
A20: South | B20: =COUNTIFS(Cleaned_Sales!D:D, A20) | C20: =SUMIFS(Cleaned_Sales!K:K, Cleaned_Sales!D:D, A20) | D20: =IFERROR(C20/B20, 0) | E20: =IF(C20>250000, "Top Market", "Developing")
A21: West | B21: =COUNTIFS(Cleaned_Sales!D:D, A21) | C21: =SUMIFS(Cleaned_Sales!K:K, Cleaned_Sales!D:D, A21) | D21: =IFERROR(C21/B21, 0) | E21: =IF(C21>250000, "Top Market", "Developing")
A24: Customer 360 Lookup (XLOOKUP & IFERROR)
A25: Select Customer Name: | B25: Aarav
A27: Assigned Region | B27: =IFERROR(XLOOKUP(B25, Dim_Customers!A:A, Dim_Customers!B:B, "Not Found"), "Error")
A28: Total Orders Placed | B28: =IFERROR(XLOOKUP(B25, Dim_Customers!A:A, Dim_Customers!C:C, 0), 0)
A29: Total Spend (₹) | B29: =IFERROR(XLOOKUP(B25, Dim_Customers!A:A, Dim_Customers!E:E, 0), 0)
A30: Average Order Value (₹) | B30: =IFERROR(XLOOKUP(B25, Dim_Customers!A:A, Dim_Customers!F:F, 0), 0)

Sheet Cleaned_Sales
A1: Order_ID | B1: Order_Date | C1: Customer | D1: Region | E1: Category | F1: Product | G1: Quantity | H1: Unit_Price | I1: Discount | J1: Payment_Status | K1: Revenue
A2: ORD2001 | B2: 2026-01-02 | C2: Aarav | D2: North | E2: Electronics | F2: Laptop | G2: 2 | H2: 55000 | I2: 0.1 | J2: Paid | K2: 99000
A3: ORD2002 | B3: 2026-01-03 | C3: Diya | D3: South | E3: Clothing | F3: Jacket | G3: 3 | H3: 4200 | I3: 0.05 | J3: Paid | K3: 11970
A4: ORD2003 | B4: 2026-01-04 | C4: Rohan | D4: West | E4: Furniture | F4: Chair | G4: 5 | H4: 3200 | I4: 0 | J4: Paid | K4: 16000
A5: ORD2004 | B5: 2026-01-05 | C5: Meera | D5: East | E5: Electronics | F5: Headphones | G5: 4 | H5: 2500 | I5: 0.15 | J5: Pending | K5: 8500
A6: ORD2005 | B6: 2026-01-06 | C6: Kabir | D6: North | E6: Furniture | F6: Table | G6: 2 | H6: 8500 | I6: 0.1 | J6: Paid | K6: 15300
A7: ORD2006 | B7: 2026-01-07 | C7: Isha | D7: South | E7: Electronics | F7: Phone | G7: 3 | H7: 28000 | I7: 0.05 | J7: Paid | K7: 79800
A8: ORD2007 | B8: 2026-01-08 | C8: Arjun | D8: West | E8: Clothing | F8: Shoes | G8: 2 | H8: 3500 | I8: 0.2 | J8: Paid | K8: 5600
A9: ORD2008 | B9: 2026-01-09 | C9: Sanya | D9: East | E9: Electronics | F9: Tablet | G9: 1 | H9: 22000 | I9: 0.1 | J9: Paid | K9: 19800
A10: ORD2009 | B10: 2026-01-10 | C10: Aarav | D10: North | E10: Electronics | F10: Laptop | G10: 1 | H10: 55000 | I10: 0.05 | J10: Paid | K10: 52250
A11: ORD2010 | B11: 2026-01-11 | C11: Diya | D11: South | E11: Clothing | F11: Jacket | G11: 4 | H11: 4200 | I11: 0.1 | J11: Failed | K11: 15120
A12: ORD2011 | B12: 2026-01-12 | C12: Rohan | D12: West | E12: Furniture | F12: Chair | G12: 3 | H12: 3200 | I12: 0.05 | J12: Paid | K12: 9120
A13: ORD2012 | B13: 2026-01-13 | C13: Meera | D13: East | E13: Electronics | F13: Headphones | G13: 5 | H13: 2500 | I13: 0 | J13: Paid | K13: 12500
... A49: ORD2050 | B49: 2026-02-21 | C49: Diya | D49: South | E49: Clothing | F49: Jacket | G49: 2 | H49: 4200 | I49: 0.05 | J49: Paid | K49: 7980

Sheet Dim_Customers
A1: Customer | B1: Region | C1: Total_Orders | D1: Total_Units | E1: Total_Revenue | F1: AOV | G1: Customer_Type
A2: Aarav | B2: North | C2: 6 | D2: 11 | E2: 539000 | F2: 89833 | G2: Repeat Buyer
A3: Isha | B3: South | C3: 6 | D3: 13 | E3: 333200 | F3: 55533 | G3: Repeat Buyer
A4: Sanya | B4: East | C4: 6 | D4: 13 | E4: 249700 | F4: 41617 | G4: Repeat Buyer
A5: Kabir | B5: North | C5: 6 | D5: 11 | E5: 83725 | F5: 13954 | G5: Repeat Buyer
A6: Rohan | B6: West | C6: 6 | D6: 23 | E6: 69920 | F6: 11653 | G6: Repeat Buyer
A7: Diya | B7: South | C7: 7 | D7: 17 | E7: 67410 | F7: 9630 | G7: Repeat Buyer
A8: Arjun | B8: West | C8: 6 | D8: 19 | E8: 58450 | F8: 9742 | G8: Repeat Buyer
A9: Meera | B9: East | C9: 5 | D9: 16 | E9: 37250 | F9: 7450 | G9: Repeat Buyer

Sheet Data_Cleaning_Audit
A1: DATA CLEANING AUDIT TRAIL (USER'S 50-ROW DATASET)
A3: Audit Checkpoint | B3: Identified Anomaly | C3: Cleaning Action Applied
A4: Initial Raw Transactions | B4: 50 | C4: Loaded raw dataset provided by user
A5: ORD2041 (Negative Quantity) | B5: Quantity = -1 | C5: Filtered out invalid order (Quantity <= 0)
A6: ORD2044 (Missing Quantity) | B6: Quantity = Blank | C6: Filtered out incomplete order (Blank Quantity)
A7: ORD2049 (Region Casing) | B7: Region = 'north' | C7: Standardized to 'North' using PROPER(TRIM())
A8: ORD2050 (Payment Status Casing) | B8: Payment_Status = 'paid' | C8: Standardized to 'Paid' using PROPER(TRIM())
A9: Discount Normalization | B9: 10%, 5%, 0% etc. | C9: Converted percentage strings into decimals (0.10, 0.05)
A10: Date Normalization | B10: 02-Jan-26 | C10: Converted DD-Mon-YY into standard ISO YYYY-MM-DD
A11: Revenue Calculation | B11: Formula Applied | C11: Revenue = Quantity * Unit_Price * (1 - Discount)
A12: Final Cleaned Records | B12: 48 Orders | C12: Validated clean dataset ready for SQL & Tableau
